artdirector.py
artdirector-0.0.3.dist-info/LICENSE
artdirector-0.0.3.dist-info/METADATA
artdirector-0.0.3.dist-info/WHEEL
artdirector-0.0.3.dist-info/entry_points.txt
artdirector-0.0.3.dist-info/top_level.txt
artdirector-0.0.3.dist-info/RECORD
