Metadata-Version: 2.1
Name: artdirector
Version: 0.0.3
Summary: Crop your image to different resolutions without missing the subject.
Home-page: https://github.com/jdnumm/artdirector
Author: Johannes Daniel Nümm
Author-email: daniel.nuemm@blacktre.es
Project-URL: Bug Tracker, https://github.com/jdnumm/artdirector/issues
Classifier: Programming Language :: Python :: 3
Classifier: License :: OSI Approved :: MIT License
Classifier: Operating System :: OS Independent
Classifier: Intended Audience :: Developers
Classifier: Topic :: Utilities
Requires-Python: >=3.6
License-File: LICENSE
Requires-Dist: Pillow >=4.0.0
